AUTHORS
INSTALL
LICENSE
MANIFEST.in
README.rst
setup.py
builder/admin.sqlite
builder/builder.sqlite
builder/demo.sqlite
builder/index.html
builder/read.me
builder/server.py
builder/css/project.css
builder/js/app_builder.js
demo/admin.sqlite
demo/demo.sqlite
demo/index.html
demo/server.py
demo/wsgi.py
demo/css/project.css
demo/js/demo.js
demo/reports/customers.ods
demo/reports/invoice.ods
demo/reports/purchases.ods
demo/static/files/SampleAudio_0.4mb2018-09-20_173200.101229.mp3
demo/static/files/adult-18792_6402018-09-20_172710.277885.jpg
demo/static/files/fashion-2082066_6402018-09-20_172551.982164.jpg
demo/static/files/girl-919048_6402018-09-20_172740.031997.jpg
demo/static/files/man-3122063_6402018-09-20_172535.467176.jpg
demo/static/files/model-2911330_6402018-09-20_172523.737081.jpg
demo/static/files/model-334739_6402018-10-03_102403.928076.jpg
demo/static/files/model-429733_6402018-09-20_175440.291794.jpg
demo/static/files/model-429733_6402019-04-25_101749.737955.jpg
demo/static/files/patient-841165_6402018-09-20_172615.389149.jpg
demo/static/files/smile-1885144_6402018-11-10_102150.945190.jpg
demo/static/files/stockvault-businessman-1282942018-09-20_172731.439691.jpg
demo/static/files/stockvault-businessman1196482018-09-20_172602.032986.jpg
demo/static/files/sun-3588618_6402018-09-20_175413.562097.jpg
demo/static/img/.gitignore
demo/static/img/JAMPY_Readme.gif
demo/static/img/j.png
demo/static/js/Chart.min.js
docs/Makefile
docs/conf.py
docs/contents.txt
docs/index.txt
docs/make.bat
docs/prepare.py
docs/set_scale.py
docs/_static/favicon.ico
docs/_static/jquery.js
docs/_templates/jamdocs/layout.html
docs/_templates/jamdocs/theme.conf
docs/_templates/jamdocs/static/bootstrap.css
docs/_templates/jamdocs/static/bootstrap.min.css
docs/_templates/jamdocs/static/default.css
docs/_templates/jamdocs/static/jamdocs.css
docs/admin/accept_string.txt
docs/admin/code_editor.txt
docs/admin/details.txt
docs/admin/index.txt
docs/admin/intergation_with_existing_database.txt
jam.py.egg-info/PKG-INFO
jam.py.egg-info/SOURCES.txt
jam.py.egg-info/dependency_links.txt
jam.py.egg-info/top_level.txt
